CHANGELOG.rst
MANIFEST.in
README.rst
default.nix
requirements-python27.txt
requirements-python36.txt
requirements-python39.txt
requirements.txt
setup.cfg
setup.nix
setup.py
tox.ini
docs/conf.py
docs/index.rst
docs/usage.rst
docs/_static/sphinxcontrib-httpexample.css
docs/_static/sphinxcontrib-httpexample.js
src/rotki_sphinxcontrib_httpexample.egg-info/PKG-INFO
src/rotki_sphinxcontrib_httpexample.egg-info/SOURCES.txt
src/rotki_sphinxcontrib_httpexample.egg-info/dependency_links.txt
src/rotki_sphinxcontrib_httpexample.egg-info/namespace_packages.txt
src/rotki_sphinxcontrib_httpexample.egg-info/not-zip-safe
src/rotki_sphinxcontrib_httpexample.egg-info/requires.txt
src/rotki_sphinxcontrib_httpexample.egg-info/top_level.txt
src/sphinxcontrib/__init__.py
src/sphinxcontrib/httpexample/__init__.py
src/sphinxcontrib/httpexample/builders.py
src/sphinxcontrib/httpexample/directives.py
src/sphinxcontrib/httpexample/parsers.py
src/sphinxcontrib/httpexample/utils.py
src/sphinxcontrib/httpexample/static/sphinxcontrib-httpexample.css
src/sphinxcontrib/httpexample/static/sphinxcontrib-httpexample.js
src/sphinxcontrib_httpexample_rotki.egg-info/PKG-INFO
src/sphinxcontrib_httpexample_rotki.egg-info/SOURCES.txt
src/sphinxcontrib_httpexample_rotki.egg-info/dependency_links.txt
src/sphinxcontrib_httpexample_rotki.egg-info/namespace_packages.txt
src/sphinxcontrib_httpexample_rotki.egg-info/not-zip-safe
src/sphinxcontrib_httpexample_rotki.egg-info/requires.txt
src/sphinxcontrib_httpexample_rotki.egg-info/top_level.txt
tests/__init__.py
tests/test_builders.py
tests/test_directives.py
tests/test_fixtures.py
tests/test_parsers.py
tests/test_utils.py
tests/fixtures/001.request.txt
tests/fixtures/001.response.txt
tests/fixtures/002.request.txt
tests/fixtures/002.response.txt
tests/fixtures/003.request.txt
tests/fixtures/003.response.txt
tests/fixtures/004.request.txt
tests/fixtures/004.response.txt
tests/fixtures/005.request.txt
tests/fixtures/005.response.txt
tests/fixtures/006.request.txt
tests/fixtures/006.response.txt
tests/fixtures/007.request.txt
tests/fixtures/007.response.txt
tests/fixtures/008.request.txt
tests/fixtures/009.request.txt
tests/fixtures/010.request.txt
tests/fixtures/011.request.txt
tests/fixtures/012.request.txt
tests/snapshots/__init__.py
tests/snapshots/snap_test_builders.py