Metadata-Version: 2.1
Name: sphinxcontrib-httpexample-rotki
Version: 0.1.1
Summary: Adds example directive for sphinx-contrib httpdomain - rotki fork
Home-page: https://github.com/rotki/sphinxcontrib-httpexample
Author: Asko Soukka
Author-email: asko.soukka@iki.fi
License: GPL version 2
Keywords: sphinx,extension,http,rest,documentation
Platform: UNKNOWN
Classifier: Development Status :: 4 - Beta
Classifier: Environment :: Console
Classifier: Environment :: Web Environment
Classifier: Framework :: Sphinx :: Extension
Classifier: Intended Audience :: Developers
Classifier: License :: OSI Approved :: GNU General Public License v2 (GPLv2)
Classifier: Operating System :: OS Independent
Classifier: Programming Language :: Python :: 2
Classifier: Programming Language :: Python :: 3
Classifier: Topic :: Documentation
Classifier: Topic :: Utilities
